{"nodes": [{"id": "home_oleg_workspace_super_app_app_lib_shared_tokens_pf_radius_dart", "label": "pf_radius.dart", "file_type": "code", "source_file": "app/lib/shared/tokens/pf_radius.dart", "source_location": null}, {"id": "tokens_pf_radius_pfradius", "label": "PfRadius", "file_type": "code", "source_file": "app/lib/shared/tokens/pf_radius.dart", "source_location": null}, {"id": "tokens_pf_radius_xs", "label": "xs", "file_type": "code", "source_file": "app/lib/shared/tokens/pf_radius.dart", "source_location": null}, {"id": "static_const_double", "label": "static const double", "file_type": "code", "source_file": null, "source_location": null}, {"id": "tokens_pf_radius_sm", "label": "sm", "file_type": "code", "source_file": "app/lib/shared/tokens/pf_radius.dart", "source_location": null}, {"id": "tokens_pf_radius_md", "label": "md", "file_type": "code", "source_file": "app/lib/shared/tokens/pf_radius.dart", "source_location": null}, {"id": "tokens_pf_radius_lg", "label": "lg", "file_type": "code", "source_file": "app/lib/shared/tokens/pf_radius.dart", "source_location": null}, {"id": "tokens_pf_radius_xl", "label": "xl", "file_type": "code", "source_file": "app/lib/shared/tokens/pf_radius.dart", "source_location": null}, {"id": "tokens_pf_radius_xxl", "label": "xxl", "file_type": "code", "source_file": "app/lib/shared/tokens/pf_radius.dart", "source_location": null}, {"id": "tokens_pf_radius_pill", "label": "pill", "file_type": "code", "source_file": "app/lib/shared/tokens/pf_radius.dart", "source_location": null}, {"id": "tokens_pf_radius_borderradiusxs", "label": "borderRadiusXs", "file_type": "code", "source_file": "app/lib/shared/tokens/pf_radius.dart", "source_location": null}, {"id": "static_const_borderradius", "label": "static const BorderRadius", "file_type": "code", "source_file": null, "source_location": null}, {"id": "tokens_pf_radius_borderradiussm", "label": "borderRadiusSm", "file_type": "code", "source_file": "app/lib/shared/tokens/pf_radius.dart", "source_location": null}, {"id": "tokens_pf_radius_borderradiusmd", "label": "borderRadiusMd", "file_type": "code", "source_file": "app/lib/shared/tokens/pf_radius.dart", "source_location": null}, {"id": "tokens_pf_radius_borderradiuslg", "label": "borderRadiusLg", "file_type": "code", "source_file": "app/lib/shared/tokens/pf_radius.dart", "source_location": null}, {"id": "tokens_pf_radius_borderradiusxl", "label": "borderRadiusXl", "file_type": "code", "source_file": "app/lib/shared/tokens/pf_radius.dart", "source_location": null}, {"id": "tokens_pf_radius_borderradiusxxl", "label": "borderRadiusXxl", "file_type": "code", "source_file": "app/lib/shared/tokens/pf_radius.dart", "source_location": null}, {"id": "tokens_pf_radius_borderradiuspill", "label": "borderRadiusPill", "file_type": "code", "source_file": "app/lib/shared/tokens/pf_radius.dart", "source_location": null}, {"id": "package_flutter_material_dart", "label": "package:flutter/material.dart", "file_type": "code", "source_file": null, "source_location": null}], "edges": [{"source": "home_oleg_workspace_super_app_app_lib_shared_tokens_pf_radius_dart", "target": "tokens_pf_radius_pfradius", "relation": "defines", "confidence": "EXTRACTED", "confidence_score": 1.0, "source_file": "app/lib/shared/tokens/pf_radius.dart", "source_location": null, "weight": 1.0}, {"source": "home_oleg_workspace_super_app_app_lib_shared_tokens_pf_radius_dart", "target": "tokens_pf_radius_xs", "relation": "defines", "confidence": "EXTRACTED", "confidence_score": 1.0, "source_file": "app/lib/shared/tokens/pf_radius.dart", "source_location": null, "weight": 1.0}, {"source": "home_oleg_workspace_super_app_app_lib_shared_tokens_pf_radius_dart", "target": "static_const_double", "relation": "references", "confidence": "EXTRACTED", "confidence_score": 1.0, "source_file": "app/lib/shared/tokens/pf_radius.dart", "source_location": null, "weight": 1.0, "context": "variable_type"}, {"source": "home_oleg_workspace_super_app_app_lib_shared_tokens_pf_radius_dart", "target": "tokens_pf_radius_sm", "relation": "defines", "confidence": "EXTRACTED", "confidence_score": 1.0, "source_file": "app/lib/shared/tokens/pf_radius.dart", "source_location": null, "weight": 1.0}, {"source": "home_oleg_workspace_super_app_app_lib_shared_tokens_pf_radius_dart", "target": "static_const_double", "relation": "references", "confidence": "EXTRACTED", "confidence_score": 1.0, "source_file": "app/lib/shared/tokens/pf_radius.dart", "source_location": null, "weight": 1.0, "context": "variable_type"}, {"source": "home_oleg_workspace_super_app_app_lib_shared_tokens_pf_radius_dart", "target": "tokens_pf_radius_md", "relation": "defines", "confidence": "EXTRACTED", "confidence_score": 1.0, "source_file": "app/lib/shared/tokens/pf_radius.dart", "source_location": null, "weight": 1.0}, {"source": "home_oleg_workspace_super_app_app_lib_shared_tokens_pf_radius_dart", "target": "static_const_double", "relation": "references", "confidence": "EXTRACTED", "confidence_score": 1.0, "source_file": "app/lib/shared/tokens/pf_radius.dart", "source_location": null, "weight": 1.0, "context": "variable_type"}, {"source": "home_oleg_workspace_super_app_app_lib_shared_tokens_pf_radius_dart", "target": "tokens_pf_radius_lg", "relation": "defines", "confidence": "EXTRACTED", "confidence_score": 1.0, "source_file": "app/lib/shared/tokens/pf_radius.dart", "source_location": null, "weight": 1.0}, {"source": "home_oleg_workspace_super_app_app_lib_shared_tokens_pf_radius_dart", "target": "static_const_double", "relation": "references", "confidence": "EXTRACTED", "confidence_score": 1.0, "source_file": "app/lib/shared/tokens/pf_radius.dart", "source_location": null, "weight": 1.0, "context": "variable_type"}, {"source": "home_oleg_workspace_super_app_app_lib_shared_tokens_pf_radius_dart", "target": "tokens_pf_radius_xl", "relation": "defines", "confidence": "EXTRACTED", "confidence_score": 1.0, "source_file": "app/lib/shared/tokens/pf_radius.dart", "source_location": null, "weight": 1.0}, {"source": "home_oleg_workspace_super_app_app_lib_shared_tokens_pf_radius_dart", "target": "static_const_double", "relation": "references", "confidence": "EXTRACTED", "confidence_score": 1.0, "source_file": "app/lib/shared/tokens/pf_radius.dart", "source_location": null, "weight": 1.0, "context": "variable_type"}, {"source": "home_oleg_workspace_super_app_app_lib_shared_tokens_pf_radius_dart", "target": "tokens_pf_radius_xxl", "relation": "defines", "confidence": "EXTRACTED", "confidence_score": 1.0, "source_file": "app/lib/shared/tokens/pf_radius.dart", "source_location": null, "weight": 1.0}, {"source": "home_oleg_workspace_super_app_app_lib_shared_tokens_pf_radius_dart", "target": "static_const_double", "relation": "references", "confidence": "EXTRACTED", "confidence_score": 1.0, "source_file": "app/lib/shared/tokens/pf_radius.dart", "source_location": null, "weight": 1.0, "context": "variable_type"}, {"source": "home_oleg_workspace_super_app_app_lib_shared_tokens_pf_radius_dart", "target": "tokens_pf_radius_pill", "relation": "defines", "confidence": "EXTRACTED", "confidence_score": 1.0, "source_file": "app/lib/shared/tokens/pf_radius.dart", "source_location": null, "weight": 1.0}, {"source": "home_oleg_workspace_super_app_app_lib_shared_tokens_pf_radius_dart", "target": "static_const_double", "relation": "references", "confidence": "EXTRACTED", "confidence_score": 1.0, "source_file": "app/lib/shared/tokens/pf_radius.dart", "source_location": null, "weight": 1.0, "context": "variable_type"}, {"source": "home_oleg_workspace_super_app_app_lib_shared_tokens_pf_radius_dart", "target": "tokens_pf_radius_borderradiusxs", "relation": "defines", "confidence": "EXTRACTED", "confidence_score": 1.0, "source_file": "app/lib/shared/tokens/pf_radius.dart", "source_location": null, "weight": 1.0}, {"source": "home_oleg_workspace_super_app_app_lib_shared_tokens_pf_radius_dart", "target": "static_const_borderradius", "relation": "references", "confidence": "EXTRACTED", "confidence_score": 1.0, "source_file": "app/lib/shared/tokens/pf_radius.dart", "source_location": null, "weight": 1.0, "context": "variable_type"}, {"source": "home_oleg_workspace_super_app_app_lib_shared_tokens_pf_radius_dart", "target": "tokens_pf_radius_borderradiussm", "relation": "defines", "confidence": "EXTRACTED", "confidence_score": 1.0, "source_file": "app/lib/shared/tokens/pf_radius.dart", "source_location": null, "weight": 1.0}, {"source": "home_oleg_workspace_super_app_app_lib_shared_tokens_pf_radius_dart", "target": "static_const_borderradius", "relation": "references", "confidence": "EXTRACTED", "confidence_score": 1.0, "source_file": "app/lib/shared/tokens/pf_radius.dart", "source_location": null, "weight": 1.0, "context": "variable_type"}, {"source": "home_oleg_workspace_super_app_app_lib_shared_tokens_pf_radius_dart", "target": "tokens_pf_radius_borderradiusmd", "relation": "defines", "confidence": "EXTRACTED", "confidence_score": 1.0, "source_file": "app/lib/shared/tokens/pf_radius.dart", "source_location": null, "weight": 1.0}, {"source": "home_oleg_workspace_super_app_app_lib_shared_tokens_pf_radius_dart", "target": "static_const_borderradius", "relation": "references", "confidence": "EXTRACTED", "confidence_score": 1.0, "source_file": "app/lib/shared/tokens/pf_radius.dart", "source_location": null, "weight": 1.0, "context": "variable_type"}, {"source": "home_oleg_workspace_super_app_app_lib_shared_tokens_pf_radius_dart", "target": "tokens_pf_radius_borderradiuslg", "relation": "defines", "confidence": "EXTRACTED", "confidence_score": 1.0, "source_file": "app/lib/shared/tokens/pf_radius.dart", "source_location": null, "weight": 1.0}, {"source": "home_oleg_workspace_super_app_app_lib_shared_tokens_pf_radius_dart", "target": "static_const_borderradius", "relation": "references", "confidence": "EXTRACTED", "confidence_score": 1.0, "source_file": "app/lib/shared/tokens/pf_radius.dart", "source_location": null, "weight": 1.0, "context": "variable_type"}, {"source": "home_oleg_workspace_super_app_app_lib_shared_tokens_pf_radius_dart", "target": "tokens_pf_radius_borderradiusxl", "relation": "defines", "confidence": "EXTRACTED", "confidence_score": 1.0, "source_file": "app/lib/shared/tokens/pf_radius.dart", "source_location": null, "weight": 1.0}, {"source": "home_oleg_workspace_super_app_app_lib_shared_tokens_pf_radius_dart", "target": "static_const_borderradius", "relation": "references", "confidence": "EXTRACTED", "confidence_score": 1.0, "source_file": "app/lib/shared/tokens/pf_radius.dart", "source_location": null, "weight": 1.0, "context": "variable_type"}, {"source": "home_oleg_workspace_super_app_app_lib_shared_tokens_pf_radius_dart", "target": "tokens_pf_radius_borderradiusxxl", "relation": "defines", "confidence": "EXTRACTED", "confidence_score": 1.0, "source_file": "app/lib/shared/tokens/pf_radius.dart", "source_location": null, "weight": 1.0}, {"source": "home_oleg_workspace_super_app_app_lib_shared_tokens_pf_radius_dart", "target": "static_const_borderradius", "relation": "references", "confidence": "EXTRACTED", "confidence_score": 1.0, "source_file": "app/lib/shared/tokens/pf_radius.dart", "source_location": null, "weight": 1.0, "context": "variable_type"}, {"source": "home_oleg_workspace_super_app_app_lib_shared_tokens_pf_radius_dart", "target": "tokens_pf_radius_borderradiuspill", "relation": "defines", "confidence": "EXTRACTED", "confidence_score": 1.0, "source_file": "app/lib/shared/tokens/pf_radius.dart", "source_location": null, "weight": 1.0}, {"source": "home_oleg_workspace_super_app_app_lib_shared_tokens_pf_radius_dart", "target": "static_const_borderradius", "relation": "references", "confidence": "EXTRACTED", "confidence_score": 1.0, "source_file": "app/lib/shared/tokens/pf_radius.dart", "source_location": null, "weight": 1.0, "context": "variable_type"}, {"source": "home_oleg_workspace_super_app_app_lib_shared_tokens_pf_radius_dart", "target": "package_flutter_material_dart", "relation": "imports", "confidence": "EXTRACTED", "confidence_score": 1.0, "source_file": "app/lib/shared/tokens/pf_radius.dart", "source_location": null, "weight": 1.0}]}